madsci/common/__init__.py
madsci/common/backup_tools/README.md
madsci/common/backup_tools/__init__.py
madsci/common/backup_tools/backup_manager.py
madsci/common/backup_tools/backup_validator.py
madsci/common/backup_tools/base_backup.py
madsci/common/backup_tools/cli.py
madsci/common/backup_tools/mongo_cli.py
madsci/common/backup_tools/mongodb_backup.py
madsci/common/backup_tools/postgres_backup.py
madsci/common/backup_tools/postgres_cli.py
madsci/common/context.py
madsci/common/data_manipulation.py
madsci/common/exceptions.py
madsci/common/manager_base.py
madsci/common/middleware.py
madsci/common/mongodb_migration_tool.py
madsci/common/mongodb_version_checker.py
madsci/common/nodes.py
madsci/common/object_storage_helpers.py
madsci/common/ownership.py
madsci/common/serializers.py
madsci/common/types/__init__.py
madsci/common/types/action_types.py
madsci/common/types/admin_command_types.py
madsci/common/types/auth_types.py
madsci/common/types/backup_types.py
madsci/common/types/base_types.py
madsci/common/types/client_types.py
madsci/common/types/condition_types.py
madsci/common/types/context_types.py
madsci/common/types/datapoint_types.py
madsci/common/types/docker_types.py
madsci/common/types/event_types.py
madsci/common/types/experiment_types.py
madsci/common/types/lab_types.py
madsci/common/types/location_types.py
madsci/common/types/manager_types.py
madsci/common/types/mongodb_migration_types.py
madsci/common/types/node_types.py
madsci/common/types/parameter_types.py
madsci/common/types/resource_types/__init__.py
madsci/common/types/resource_types/custom_types.py
madsci/common/types/resource_types/definitions.py
madsci/common/types/resource_types/resource_enums.py
madsci/common/types/resource_types/server_types.py
madsci/common/types/step_types.py
madsci/common/types/workcell_types.py
madsci/common/types/workflow_types.py
madsci/common/utils.py
madsci/common/validators.py
madsci/common/warnings.py
madsci/common/workflows.py
madsci_common-0.6.1.dist-info/METADATA
madsci_common-0.6.1.dist-info/WHEEL
madsci_common-0.6.1.dist-info/entry_points.txt
madsci_common-0.6.1.dist-info/RECORD
