Metadata-Version: 2.1
Name: madsci.common
Version: 0.6.1
Summary: The Modular Autonomous Discovery for Science (MADSci) Common Definitions and Utilities.
Author-Email: Tobias Ginsburg <tginsburg@anl.gov>, "Ryan D. Lewis" <ryan.lewis@anl.gov>, Casey Stone <cstone@anl.gov>, Doga Ozgulbas <dozgulbas@anl.gov>
License: MIT
Project-URL: Homepage, https://github.com/AD-SDL/MADSci
Requires-Python: >=3.9.1
Requires-Dist: pydantic>=2.10
Requires-Dist: PyYAML>=6.0.2
Requires-Dist: sqlmodel>=0.0.22
Requires-Dist: python-ulid[pydantic]>=3.0.0
Requires-Dist: aenum>=3.1.15
Requires-Dist: python-dotenv>=1.0.1
Requires-Dist: requests>=2.32.3
Requires-Dist: pymongo>=4.10.1
Requires-Dist: psycopg2-binary>=2.9.0
Requires-Dist: fastapi>=0.115.4
Requires-Dist: uvicorn[standard]>=0.32.0
Requires-Dist: python-multipart>=0.0.17
Requires-Dist: pydantic-extra-types>=2.10.2
Requires-Dist: semver>=3.0.4
Requires-Dist: multiprocess>=0.70.17
Requires-Dist: pydantic-settings>=2.9.1
Requires-Dist: pydantic-settings-export>=1.0.2
Requires-Dist: regex>=2025.7.34
Requires-Dist: classy-fastapi>=0.7.0
Requires-Dist: httpx>=0.28.1
Requires-Dist: click>=8.1.0
